friendli_app/__init__.py
friendli_app/main.py
friendli_app/cli/app.py
friendli_app/cli/const.py
friendli_app/cli/context.py
friendli_app/cli/friendli_cli.py
friendli_app/cli/action/__init__.py
friendli_app/cli/action/app_deploy.py
friendli_app/cli/action/app_list.py
friendli_app/cli/action/app_restart.py
friendli_app/cli/action/app_terminate.py
friendli_app/cli/action/app_update.py
friendli_app/cli/action/version.py
friendli_app/cli/action/whoami.py
friendli_app/cli/backend/__init__.py
friendli_app/cli/backend/auth/__init__.py
friendli_app/cli/backend/settings/__init__.py
friendli_app/cli/backend/settings/schema.py
friendli_app/cli/command/__init__.py
friendli_app/cli/command/agent.py
friendli_app/cli/command/auth.py
friendli_app/cli/command/version.py
friendli_app/cli/schema/__init__.py
friendli_app/cli/schema/_base.py
friendli_app/cli/schema/user.py
friendli_app/cli/typer_util/__init__.py
friendli_app/cli/typer_util/builder.py
friendli_app/cli/typer_util/context.py
friendli_app/cli/typer_util/help_text.py
friendli_app/cli/typer_util/trogon.py
friendli_app/cli/typer_util/typing.py
friendli_app/cli/util/__init__.py
friendli_app/cli/util/file_utils.py
friendli_app/cli/util/random_name.py
friendli_app/cli/util/humanize/__init__.py
friendli_app/cli/util/humanize/bytes.py
friendli_app/cli/util/humanize/datetime.py
friendli_app/sdk/__init__.py
friendli_app/sdk/app.py
friendli_app-0.0.3.dist-info/METADATA
friendli_app-0.0.3.dist-info/WHEEL
friendli_app-0.0.3.dist-info/entry_points.txt
friendli_app-0.0.3.dist-info/top_level.txt
friendli_app-0.0.3.dist-info/RECORD
