Metadata-Version: 2.4
Name: friendli-app
Version: 0.0.3
Summary: Friendli App - AI agent framework with CLI and SDK
Author-email: FriendliAI Teams <eng@friendli.ai>
License-Expression: MIT
Requires-Python: >=3.11
Requires-Dist: typer>=0.15.0
Requires-Dist: rich>=13.9.0
Requires-Dist: pydantic>=2.10.0
Requires-Dist: httpx[http2]>=0.28.0
Requires-Dist: trogon>=0.6.0
Requires-Dist: questionary>=2.0.1
Requires-Dist: graphql-core>=3.2.5
Requires-Dist: websockets>=14.0
Requires-Dist: eval-type-backport>=0.2.0
Requires-Dist: fastapi>=0.115.0
Requires-Dist: uvicorn[standard]>=0.32.0
Requires-Dist: starlette>=0.41.0
